<?xml version="1.0" encoding="UTF-8" ?>
<!DOCTYPE mapper PUBLIC "-//mybatis.org//DTD Mapper 3.0//EN" "http://mybatis.org/dtd/mybatis-3-mapper.dtd"> 

<mapper namespace="mpListPublication">

    <resultMap id="mpListPublicationResult" type="mpListPublication" extends="base.result">
        <id property="id" column="mp_list_publication_id"/>
        <association property="mpList" column="mp_list_id" select="mpList.getById"/>
        <association property="mpPublication" column="publication_id" select="mpPublication.getById"/>
    </resultMap>

    <sql id="cols">
        mp_list_publication_id, mp_list_id, publication_id,
        <include refid="base.auditCols"/>
    </sql>

    <sql id="hosts">
        #{id,jdbcType=INTEGER},
        #{mpList.id,jdbcType=INTEGER},
        #{mpPublication.id,jdbcType=INTEGER},
        <include refid="base.auditHosts"/>
    </sql>

    <sql id="sets">
        mp_list_id = #{mpList.id,jdbcType=INTEGER},
        publication_id = #{mpPublication.id,jdbcType=INTEGER},
        <include refid="base.auditSets"/>
    </sql>

    <insert id="add" parameterType="mpListPublication">
        <selectKey keyProperty="id" resultType="Integer" order="BEFORE">
            select nextval('mp_list_publication_seq')
        </selectKey>
        insert into mp_list_publication (<include refid="cols"/>)
            values (<include refid="hosts"/>)
    </insert>

    <sql id="baseSelect">
        select <include refid="cols"/>
          from mp_list_publication
    </sql>

    <sql id="filters">
        <where>
            <if test="publicationId != null">
                and publication_id = #{publicationId}
            </if>
            <if test="mpListId != null">
                and mp_list_id = #{mpListId}
            </if>
        </where>
    </sql>

    <select id="getById" parameterType="Integer" resultMap="mpListPublicationResult">
        <include refid="baseSelect"/>
         where mp_list_publication_id = #{id,jdbcType=INTEGER}
    </select>

    <select id="getByMap" parameterType="Integer" resultMap="mpListPublicationResult">
        <include refid="baseSelect"/>
        <include refid="filters"/>
    </select>

    <update id="update" parameterType="mpListPublication">
        update mp_list_publication
           set <include refid="sets"/>
         where mp_list_publication_id = #{id,jdbcType=INTEGER}
    </update>
    
    <delete id="delete" parameterType="Integer">
        delete from mp_list_publication <include refid="base.deleteAuditHack"/>
         where mp_list_publication_id = #{value,jdbcType=INTEGER}
    </delete>

    <delete id="deleteByParent" parameterType="Integer">
        delete from mp_list_publication <include refid="base.deleteAuditHack"/>
         where publication_id = #{value,jdbcType=INTEGER}
    </delete>

</mapper>
